contextinator/__init__.py
contextinator/__main__.py
contextinator/_version.py
contextinator/cli.py
contextinator/chunking/__init__.py
contextinator/chunking/ast_parser.py
contextinator/chunking/ast_visualizer.py
contextinator/chunking/chunk_service.py
contextinator/chunking/context_builder.py
contextinator/chunking/file_discovery.py
contextinator/chunking/node_collector.py
contextinator/chunking/notebook_parser.py
contextinator/chunking/splitter.py
contextinator/config/__init__.py
contextinator/config/settings.py
contextinator/embedding/__init__.py
contextinator/embedding/embedding_service.py
contextinator/ingestion/__init__.py
contextinator/ingestion/async_service.py
contextinator/tools/__init__.py
contextinator/tools/cat_file.py
contextinator/tools/grep_search.py
contextinator/tools/repo_structure.py
contextinator/tools/semantic_search.py
contextinator/tools/symbol_search.py
contextinator/utils/__init__.py
contextinator/utils/exceptions.py
contextinator/utils/hash_utils.py
contextinator/utils/logger.py
contextinator/utils/output_formatter.py
contextinator/utils/progress.py
contextinator/utils/repo_utils.py
contextinator/utils/rich_help.py
contextinator/utils/token_counter.py
contextinator/utils/toon_encoder.py
contextinator/vectorstore/__init__.py
contextinator/vectorstore/async_chroma.py
contextinator/vectorstore/chroma_store.py
contextinator-1.2.3.dist-info/licenses/LICENSE
contextinator-1.2.3.dist-info/METADATA
contextinator-1.2.3.dist-info/WHEEL
contextinator-1.2.3.dist-info/entry_points.txt
contextinator-1.2.3.dist-info/top_level.txt
contextinator-1.2.3.dist-info/RECORD
