Metadata-Version: 2.4
Name: contextinator
Version: 1.2.3
Summary: Intelligent Codebase Understanding for AI Agents - Transform any codebase into semantically-aware, searchable knowledge
Author-email: STARTHACK Team <founders@starthack.io>
License: Apache-2.0
Project-URL: Homepage, https://github.com/starthackHQ/Contextinator
Project-URL: Documentation, https://github.com/starthackHQ/Contextinator/docs
Project-URL: Repository, https://github.com/starthackHQ/Contextinator
Project-URL: Issues, https://github.com/starthackHQ/Contextinator/issues
Keywords: ai,code-analysis,ast,embeddings,vector-search,semantic-search,codebase,tree-sitter,chromadb
Classifier: Development Status :: 3 - Alpha
Classifier: Intended Audience :: Developers
Classifier: License :: OSI Approved :: Apache Software License
Classifier: Operating System :: OS Independent
Classifier: Programming Language :: Python :: 3.10
Classifier: Programming Language :: Python :: 3.11
Classifier: Programming Language :: Python :: 3.12
Classifier: Programming Language :: Python :: 3.13
Classifier: Topic :: Software Development :: Code Generators
Classifier: Topic :: Software Development :: Libraries :: Python Modules
Classifier: Topic :: Scientific/Engineering :: Artificial Intelligence
Requires-Python: >=3.10
License-File: LICENSE
Requires-Dist: tree-sitter>=0.25.0
Requires-Dist: chromadb>=1.3.0
Requires-Dist: openai>=2.6.0
Requires-Dist: tiktoken>=0.12.0
Requires-Dist: python-dotenv>=1.2.0
Requires-Dist: flask>=3.1.0
Requires-Dist: requests>=2.32.0
Requires-Dist: rich>=13.0.0
Requires-Dist: toon-format>=0.9.0b1
Requires-Dist: nbformat>=5.0.0
Requires-Dist: tree-sitter-python>=0.25.0
Requires-Dist: tree-sitter-javascript>=0.25.0
Requires-Dist: tree-sitter-typescript>=0.23.0
Requires-Dist: tree-sitter-java>=0.23.0
Requires-Dist: tree-sitter-go>=0.25.0
Requires-Dist: tree-sitter-rust>=0.24.0
Requires-Dist: tree-sitter-cpp>=0.23.0
Requires-Dist: tree-sitter-c>=0.24.0
Requires-Dist: tree-sitter-c-sharp>=0.23.0
Requires-Dist: tree-sitter-php>=0.24.0
Requires-Dist: tree-sitter-bash>=0.25.0
Requires-Dist: tree-sitter-sql>=0.3.0
Requires-Dist: tree-sitter-kotlin>=1.1.0
Requires-Dist: tree-sitter-yaml>=0.7.0
Requires-Dist: tree-sitter-markdown>=0.5.0
Requires-Dist: tree-sitter-json>=0.24.0
Requires-Dist: tree-sitter-toml>=0.7.0
Requires-Dist: tree-sitter-swift>=0.0.1
Requires-Dist: tree-sitter-solidity>=1.2.0
Requires-Dist: tree-sitter-lua>=0.2.0
Requires-Dist: tree-sitter-html>=0.23.0
Requires-Dist: tree-sitter-css>=0.25.0
Requires-Dist: tree-sitter-zig>=1.1.0
Requires-Dist: tree-sitter-ruby>=0.23.0
Requires-Dist: tree-sitter-scala>=0.24.0
Requires-Dist: tree-sitter-haskell>=0.23.0
Requires-Dist: tree-sitter-ocaml>=0.24.0
Requires-Dist: tree-sitter-elixir>=0.3.0
Requires-Dist: tree-sitter-hcl>=1.2.0
Requires-Dist: tree-sitter-make>=1.1.0
Requires-Dist: tree-sitter-xml>=0.7.0
Requires-Dist: ruff>=0.14.10
Provides-Extra: extended-parsers
Requires-Dist: tree-sitter-dockerfile>=0.0.0a1; platform_system != "Windows" and extra == "extended-parsers"
Requires-Dist: tree-sitter-embedded-template>=0.25.0; extra == "extended-parsers"
Provides-Extra: dev
Requires-Dist: pytest>=7.0.0; extra == "dev"
Requires-Dist: pytest-cov>=4.0.0; extra == "dev"
Requires-Dist: black>=23.0.0; extra == "dev"
Requires-Dist: flake8>=6.0.0; extra == "dev"
Requires-Dist: mypy>=1.0.0; extra == "dev"
Requires-Dist: pre-commit>=3.0.0; extra == "dev"
Provides-Extra: docs
Requires-Dist: myst-parser>=2.0.0; extra == "docs"
Dynamic: license-file
